papygo/__init__.py
papygo/translator.py
papygo-1.0.2.dist-info/LICENSE
papygo-1.0.2.dist-info/METADATA
papygo-1.0.2.dist-info/WHEEL
papygo-1.0.2.dist-info/top_level.txt
papygo-1.0.2.dist-info/RECORD
