Metadata-Version: 2.1
Name: papygo
Version: 1.0.2
Summary: A simple library for translating using the NAVER Papago API
Home-page: https://github.com/gaon12/papygo
Author: Jeong Gaon
Author-email: gokirito12@gmail.com
Classifier: Programming Language :: Python :: 3
Classifier: License :: OSI Approved :: MIT License
Classifier: Operating System :: OS Independent
Classifier: Programming Language :: Python :: 3.6
Classifier: Programming Language :: Python :: 3.7
Classifier: Programming Language :: Python :: 3.8
Classifier: Programming Language :: Python :: 3.9
Classifier: Programming Language :: Python :: 3.10
Classifier: Programming Language :: Python :: 3.11
Classifier: Programming Language :: Python :: 3.12
Requires-Python: >=3.6
License-File: LICENSE
Requires-Dist: urllib3 >=1.25.3
